pushi/__init__.py
pushi/api/__init__.py
pushi/api/apn.py
pushi/api/app.py
pushi/api/base.py
pushi/api/event.py
pushi/api/subscription.py
pushi/api/web.py
pushi/app/__init__.py
pushi/app/__main__.py
pushi/app/base.py
pushi/app/controllers/__init__.py
pushi/app/controllers/apn.py
pushi/app/controllers/app.py
pushi/app/controllers/base.py
pushi/app/controllers/event.py
pushi/app/controllers/health.py
pushi/app/controllers/smtp.py
pushi/app/controllers/socket.py
pushi/app/controllers/subscription.py
pushi/app/controllers/web.py
pushi/app/controllers/web_push.py
pushi/app/models/__init__.py
pushi/app/models/apn.py
pushi/app/models/app.py
pushi/app/models/association.py
pushi/app/models/base.py
pushi/app/models/event.py
pushi/app/models/smtp.py
pushi/app/models/subscription.py
pushi/app/models/web.py
pushi/app/models/web_push.py
pushi/base/__init__.py
pushi/base/__main__.py
pushi/base/apn.py
pushi/base/handler.py
pushi/base/smtp.py
pushi/base/state.py
pushi/base/web.py
pushi/base/web_push.py
pushi/net/__init__.py
pushi/net/client.py
pushi/net/server.py
pushi/test/__init__.py
pushi/test/base.py
pushi/test/health.py
pushi/test/web_push.py
pushi_service-0.5.1.dist-info/METADATA
pushi_service-0.5.1.dist-info/WHEEL
pushi_service-0.5.1.dist-info/top_level.txt
pushi_service-0.5.1.dist-info/RECORD
